{
	"navigation": {
		"UP": ["ArrowUp"],
		"DOWN": ["ArrowDown"],
		"LEFT": ["ArrowLeft"],
		"RIGHT": ["ArrowRight"],
		"GOTO": ["g"]
	},
	"canvas": {
		"STITCH": ["Space", "Enter"],
		"UNSTITCH": ["Backspace", "Delete"],
		"UNSTITCH_MOD": ["Ctrl+Space"],
		"EYEDROPPER": ["i", "Alt+Space"],
		"SOAK": ["f"],
		"BIND_VERTEX": ["Shift+Enter"],
		"SEAL_BINDING": ["Enter"]
	},
	"history": {
		"UNDO": ["Ctrl+z"],
		"REDO": ["Ctrl+Shift+z", "Ctrl+y"]
	},
	"manipulation": {
		"COPY": ["Ctrl+c"],
		"CUT": ["Ctrl+x"],
		"PASTE": ["Ctrl+v"],
		"BLEACH": ["Alt+r"],
		"FLIP_H": ["h"],
		"FLIP_V": ["v"],
		"ROTATE": ["r"]
	},
	"view": {
		"ZOOM_IN": ["+", "="],
		"ZOOM_OUT": ["-"],
		"RESET_ZOOM": ["Ctrl+0"]
	},
	"studio": {
		"COMMAND_PALETTE": ["Ctrl+k"],
		"EXPORT": ["Ctrl+e"],
		"SAVE": ["Ctrl+s"],
		"OPEN": ["Ctrl+o"],
		"SETTINGS": ["Ctrl+,"],
		"COLOR_PICKER": ["Ctrl+p"],
		"AUDIO_SETTINGS": ["Ctrl+Shift+a"],
		"USER_GUIDE": ["F1"],
		"QUICK_GUIDE": ["F2"],
		"PLAY_PULSE": ["p"],
		"CLEAR_LINEN": ["Ctrl+l"],
		"TOGGLE_MUTE": ["Ctrl+m"],
		"ESCAPE": ["Escape"]
	},
	"palette": {
		"SELECT_1": ["1"],
		"SELECT_2": ["2"],
		"SELECT_3": ["3"],
		"SELECT_4": ["4"],
		"SELECT_5": ["5"],
		"SELECT_6": ["6"],
		"SELECT_7": ["7"],
		"SELECT_8": ["8"],
		"SELECT_9": ["9"],
		"SELECT_0": ["0"]
	},
	"folio": {
		"NEW_FRAME": ["Alt+n"],
		"NEXT_FRAME": ["Alt+PageDown", "Tab"],
		"PREV_FRAME": ["Alt+PageUp", "Shift+Tab"],
		"DELETE_FRAME": ["Alt+Backspace"]
	},
	"veils": {
		"NEW_VEIL": ["Alt+Shift+n"],
		"NEXT_VEIL": ["Alt+ArrowDown"],
		"PREV_VEIL": ["Alt+ArrowUp"],
		"TOGGLE_VEIL_LOCK": ["Alt+l"],
		"TOGGLE_VEIL_VISIBILITY": ["Alt+h"],
		"MERGE_VEILS": ["Alt+m"],
		"MOVE_VEIL_UP": ["["],
		"MOVE_VEIL_DOWN": ["]"],
		"DELETE_VEIL": ["Alt+Shift+Backspace"]
	},
	"modifiers": {
		"FLOW_STITCH": ["Control"],
		"FLOW_UNSTITCH": ["Ctrl+Shift"],
		"FLOW_SELECT": ["Shift"],
		"SPIRIT_PICK": ["w"]
	},
	"reserved_do_not_use": {
		"OS_CLOSE_WINDOW": ["Ctrl+w"],
		"OS_QUIT": ["Ctrl+q", "Alt+f4"],
		"OS_NEW_WINDOW": ["Ctrl+n"],
		"OS_RELOAD": ["Ctrl+r", "F5"],
		"OS_DEV_TOOLS": ["Ctrl+Shift+i", "F12"],
		"OS_FIND": ["Ctrl+f"],
		"OS_PRINT": ["Ctrl+p", "Ctrl+Shift+p"],
		"OS_FULLSCREEN": ["F11"]
	}
}
